{
  "hero": [
    {
      "id": "Bachelor (2020) MPrime Originals",
      "title": "Bachelor (2020) MPrime Originals",
      "poster": "https://ingfree.xyz/ib/bgaMgEwBVy.jpg",
      "stream_url": "https://arabic.ydc1wes.me/hls2/01/00000/xcc4fhj7vkz9_,l,o,.urlset/master.m3u8?t=TAwg8o3q3uQxelU-LNrNzhgJrIXAzioTvBOLG0aqqlo&s=1778235562&e=21600&f=3425&i=0.0&sp=0",
      "headers": {
        "Referer": "https://speedostream1.com/"
      }
    }
  ],
  "categories": [
    {
      "name": "Latest from input11.json",
      "items": [
        {
          "id": "Bachelor (2020) MPrime Originals",
          "title": "Bachelor (2020) MPrime Originals",
          "poster": "https://ingfree.xyz/ib/bgaMgEwBVy.jpg",
          "stream_url": "https://arabic.ydc1wes.me/hls2/01/00000/xcc4fhj7vkz9_,l,o,.urlset/master.m3u8?t=TAwg8o3q3uQxelU-LNrNzhgJrIXAzioTvBOLG0aqqlo&s=1778235562&e=21600&f=3425&i=0.0&sp=0",
          "headers": {
            "Referer": "https://speedostream1.com/"
          }
        },
        {
          "id": "Night Fall (2020) MPrime Originals",
          "title": "Night Fall (2020) MPrime Originals",
          "poster": "https://ingfree.xyz/ib/UHCcd8Sh07.jpg",
          "stream_url": "https://arabic.ydc1wes.me/hls2/01/00000/kdbaegzqzi7a_,l,o,.urlset/master.m3u8?t=IdmDnJC26BnrcOJ0CyovBzA9RQujvy6AFeqcGjMcpvo&s=1778235564&e=21600&f=3403&i=0.0&sp=0",
          "headers": {
            "Referer": "https://speedostream1.com/"
          }
        },
        {
          "id": "Contract (2020) Season 1 Episode 2 MPrime Originals",
          "title": "Contract (2020) Season 1 Episode 2 MPrime Originals",
          "poster": "https://ingfree.xyz/ib/gnYK4kfUkw.jpg",
          "stream_url": "https://arabic.ydc1wes.me/hls2/01/00000/sjh3afvcl37i_,l,o,.urlset/master.m3u8?t=7lnoGVH3LwYJX0EYLxYe1-12-3T3Ay3aXWbejoa1OWE&s=1778235565&e=21600&f=3290&i=0.0&sp=0",
          "headers": {
            "Referer": "https://speedostream1.com/"
          }
        },
        {
          "id": "Lappy Girl (2020) MPrime Originals",
          "title": "Lappy Girl (2020) MPrime Originals",
          "poster": "https://ingfree.xyz/ib/SMLtgFoNSK.jpg",
          "stream_url": "https://dawn.ydc1wes.me/hls2/02/00000/eoevu3uuvkx4_,l,o,.urlset/master.m3u8?t=e_ccCt2d_2goEVwSxRZrvde-i_gsiC_ONxOUIBFQ_Mo&s=1778235566&e=21600&f=3230&i=161.248&sp=0",
          "headers": {
            "Referer": "https://speedostream1.com/"
          }
        },
        {
          "id": "Sexy Machanic (2020) MPrime Originals",
          "title": "Sexy Machanic (2020) MPrime Originals",
          "poster": "https://ingfree.xyz/ib/2XL092ZLYC.jpg",
          "stream_url": "https://dawn.ydc1wes.me/hls2/02/00000/gwfb107pk98p_,l,o,.urlset/master.m3u8?t=SwkRIZrP1yB7KWNrvxp1VrtazTgGjFR91MTPicwKBpQ&s=1778235567&e=21600&f=3103&i=161.248&sp=0",
          "headers": {
            "Referer": "https://speedostream1.com/"
          }
        },
        {
          "id": "Hila Hila K (2020) MPrime Originals",
          "title": "Hila Hila K (2020) MPrime Originals",
          "poster": "https://ingfree.xyz/ib/i8UpTsbqxi.jpg",
          "stream_url": "https://dawn.ydc1wes.me/hls2/02/00000/d4bekaq5xq8o_,l,o,.urlset/master.m3u8?t=vC4me3sEObQntw7krCzBh2w8P9wgqUp4wcsUugDLDyA&s=1778235569&e=21600&f=2882&i=0.0&sp=0",
          "headers": {
            "Referer": "https://speedostream1.com/"
          }
        },
        {
          "id": "Desi Love (2020) MPrime Originals",
          "title": "Desi Love (2020) MPrime Originals",
          "poster": "https://ingfree.xyz/ib/g6FBxcPDII.jpg",
          "stream_url": "https://dawn.ydc1wes.me/hls2/02/00000/fi8x506k7q5v_,l,o,.urlset/master.m3u8?t=H1kVgX3N2noTrpyXv3uMFO9-AcKuoqMgpiMZKxUargA&s=1778235570&e=21600&f=2710&i=0.0&sp=0",
          "headers": {
            "Referer": "https://speedostream1.com/"
          }
        },
        {
          "id": "Self Satisfaction (2020) MPrime Originals",
          "title": "Self Satisfaction (2020) MPrime Originals",
          "poster": "https://ingfree.xyz/ib/B1OjimTY6e.jpg",
          "stream_url": "https://abella.ydc1wes.me/hls2/02/00000/94i3wl3mwllh_,l,o,.urlset/master.m3u8?t=9aVM7Ow23CZKQm1LR1dvzzF1lsmWkarcDYnOT79qnP8&s=1778235571&e=21600&f=2249&i=161.248&sp=0",
          "headers": {
            "Referer": "https://speedostream1.com/"
          }
        },
        {
          "id": "Fir Koi Aur (2020) MPrime Originals",
          "title": "Fir Koi Aur (2020) MPrime Originals",
          "poster": "https://ingfree.xyz/ib/lhxqJKdbW3.jpg",
          "stream_url": "https://abella.ydc1wes.me/hls2/01/00000/694a01tuuu04_o/master.m3u8?t=l_zOEfN6tV8-yCcUNDVjcTk7_XP8afOWePdl1ebakNA&s=1778235572&e=21600&f=2125&i=0.0&sp=0",
          "headers": {
            "Referer": "https://speedostream1.com/"
          }
        },
        {
          "id": "Contract (2020) Season 1 Episode 1 MPrime Originals",
          "title": "Contract (2020) Season 1 Episode 1 MPrime Originals",
          "poster": "https://ingfree.xyz/ib/gnYK4kfUkw.jpg",
          "stream_url": "https://abella.ydc1wes.me/hls2/02/00000/56oiql9ilac3_,l,o,.urlset/master.m3u8?t=m_LP4btminJTKEsjCV0KwZ8XsBraDDAG7daA8M_KucY&s=1778235573&e=21600&f=2000&i=161.248&sp=0",
          "headers": {
            "Referer": "https://speedostream1.com/"
          }
        },
        {
          "id": "Saazish (2020) MPrime Originals",
          "title": "Saazish (2020) MPrime Originals",
          "poster": "https://ingfree.xyz/ib/EcP4lNBjAz.jpg",
          "stream_url": "https://abella.ydc1wes.me/hls2/02/00000/pxt1gp7arp5r_,l,o,.urlset/master.m3u8?t=RV0D6elFHT8Ce8qRmZ17KNTsT7vKxZ0Cp7ROUvcx5lA&s=1778235574&e=21600&f=1885&i=0.0&sp=0",
          "headers": {
            "Referer": "https://speedostream1.com/"
          }
        },
        {
          "id": "Teachers Birthday (2020) Season 1 Episode 3 Masti Prime Originals",
          "title": "Teachers Birthday (2020) Season 1 Episode 3 Masti Prime Originals",
          "poster": "https://ingfree.xyz/ib/M65MLmWyRx.jpg",
          "stream_url": "https://abella.ydc1wes.me/hls2/02/00000/bt545nrd89ry_,l,n,.urlset/master.m3u8?t=FfioUsX_RhEM75KTyuYuRo3SVdfP0UZqFvo4Dw8tOm8&s=1778235576&e=21600&f=1349&i=0.0&sp=0",
          "headers": {
            "Referer": "https://speedostream1.com/"
          }
        },
        {
          "id": "The Final Destiny (2020) MPrime Originals",
          "title": "The Final Destiny (2020) MPrime Originals",
          "poster": "https://ingfree.xyz/ib/GOZlhK9laB.jpg",
          "stream_url": "https://dawn.ydc1wes.me/hls2/02/00000/6xdebw607234_o/master.m3u8?t=sMqPxzlb3qfW8JyJ7Se7iv4eRmiYweG0hRTloXXE3JI&s=1778235579&e=21600&f=124&i=0.0&sp=0",
          "headers": {
            "Referer": "https://speedostream1.com/"
          }
        },
        {
          "id": "Teachers Birthday (2020) Season 1 Episode 2 Masti Prime Originals",
          "title": "Teachers Birthday (2020) Season 1 Episode 2 Masti Prime Originals",
          "poster": "https://ingfree.xyz/ib/M65MLmWyRx.jpg",
          "stream_url": "https://dawn.ydc1wes.me/hls2/02/00000/ufg7tuacllsa_o/master.m3u8?t=PGqzYy6heYaBLBsk01EPdcbVPzaYihG-dPOuJp-X5L0&s=1778235580&e=21600&f=169&i=0.0&sp=0",
          "headers": {
            "Referer": "https://speedostream1.com/"
          }
        },
        {
          "id": "Love Bites (2020) Masti Prime Originals",
          "title": "Love Bites (2020) Masti Prime Originals",
          "poster": "https://ingfree.xyz/ib/UVrJKdSVYw.jpg",
          "stream_url": "https://abella.ydc1wes.me/hls2/02/00000/3tbwswcletux_o/master.m3u8?t=twv_-DlEPQHG-fxrYyjknUabfOskQ3ljUsIi8FaEtdA&s=1778235582&e=21600&f=210&i=0.0&sp=0",
          "headers": {
            "Referer": "https://speedostream1.com/"
          }
        },
        {
          "id": "Teachers Birthday (2020) Season 1 Episode 1 Masti Prime Originals",
          "title": "Teachers Birthday (2020) Season 1 Episode 1 Masti Prime Originals",
          "poster": "https://ingfree.xyz/ib/M65MLmWyRx.jpg",
          "stream_url": "https://abella.ydc1wes.me/hls2/02/00000/kzst3kvp18j8_,n,o,.urlset/master.m3u8?t=AT9gyaoOG52XtBrwxNdRTDIC9kyUqgxEpp59TNF5wz0&s=1778235583&e=21600&f=232&i=0.0&sp=0",
          "headers": {
            "Referer": "https://speedostream1.com/"
          }
        },
        {
          "id": "Lockdown Problem (2020) Masti Prime Originals",
          "title": "Lockdown Problem (2020) Masti Prime Originals",
          "poster": "https://ingfree.xyz/ib/a23Mybi9vw.png",
          "stream_url": "https://abella.ydc1wes.me/hls2/02/00000/7jcb47nm45hi_,n,o,.urlset/master.m3u8?t=Il9H76JhCNhjCWM07dlOVVTCy54qC9Tva00BiX-WXfU&s=1778235584&e=21600&f=262&i=0.0&sp=0",
          "headers": {
            "Referer": "https://speedostream1.com/"
          }
        },
        {
          "id": "Bedsheet (2020) Masti Prime Originals",
          "title": "Bedsheet (2020) Masti Prime Originals",
          "poster": "https://ingfree.xyz/ib/r4m4VjBLka.jpg",
          "stream_url": "https://dawn.ydc1wes.me/hls2/02/00000/od3tu31l8m9e_,n,o,.urlset/master.m3u8?t=saQe-X-r6tkXQ4md0cvqdScdF0UAGMYb5bwNkt6lOew&s=1778235588&e=21600&f=319&i=0.0&sp=0",
          "headers": {
            "Referer": "https://speedostream1.com/"
          }
        },
        {
          "id": "One Night Stand (2020) Masti Prime Originals",
          "title": "One Night Stand (2020) Masti Prime Originals",
          "poster": "https://ingfree.xyz/ib/NXEDZ06Oj7.jpg",
          "stream_url": "https://ritchie.ydc1wes.me/hls2/02/00000/07ikbear54ze_n/master.m3u8?t=85Sc4yQwM_lNcMqEgpYqiXyNx_Xk1j3y30VsrFdoiJQ&s=1778235589&e=21600&f=479&i=0.0&sp=0",
          "headers": {
            "Referer": "https://speedostream1.com/"
          }
        },
        {
          "id": "Pyasi Teacher (2020) Masti Prime Originals",
          "title": "Pyasi Teacher (2020) Masti Prime Originals",
          "poster": "https://ingfree.xyz/ib/Ifp8ZlmsL4.jpg",
          "stream_url": "https://dawn.ydc1wes.me/hls2/02/00000/g2ti8wmt2lka_,n,o,.urlset/master.m3u8?t=mtERZhuhqwhRuLzdsI37BU6iel-0CadqvF6KZuIMEeU&s=1778235590&e=21600&f=419&i=0.0&sp=0",
          "headers": {
            "Referer": "https://speedostream1.com/"
          }
        },
        {
          "id": "Naughty Boudi (2020) Masti Prime Originals",
          "title": "Naughty Boudi (2020) Masti Prime Originals",
          "poster": "https://ingfree.xyz/ib/ozjfq3wvkP.png",
          "stream_url": "https://dawn.ydc1wes.me/hls2/02/00000/4k934z5jpcpl_,l,o,.urlset/master.m3u8?t=o-VCQtwN4w2ZuPc7KK7U6Ram62CDmAb2aWBao-3RyRw&s=1778235591&e=21600&f=435&i=0.0&sp=0",
          "headers": {
            "Referer": "https://speedostream1.com/"
          }
        },
        {
          "id": "Poison (2020) Masti Prime Originals",
          "title": "Poison (2020) Masti Prime Originals",
          "poster": "https://ingfree.xyz/ib/AgRXXAJzIh.png",
          "stream_url": "https://dawn.ydc1wes.me/hls2/02/00000/ylz46wmoa9ew_,n,o,.urlset/master.m3u8?t=zU_KuyW0pFDTZwOg9OBIZXk_T3tT9aoLZ_jBrAcaiwA&s=1778235592&e=21600&f=430&i=0.0&sp=0",
          "headers": {
            "Referer": "https://speedostream1.com/"
          }
        },
        {
          "id": "MMS (2020) Masti Prime Originals",
          "title": "MMS (2020) Masti Prime Originals",
          "poster": "https://ingfree.xyz/ib/ZHAKmGtzIg.jpg",
          "stream_url": "https://dawn.ydc1wes.me/hls2/02/00000/fkdxzvcvql7q_n/master.m3u8?t=QZr9NzzW1euw3NRnX1KgEkHVEIoS0UiofJgbprsoxs8&s=1778235594&e=21600&f=438&i=0.0&sp=0",
          "headers": {
            "Referer": "https://speedostream1.com/"
          }
        }
      ]
    }
  ]
}